proclamation/__init__.py
proclamation/main.py
proclamation/merge.py
proclamation/project.py
proclamation/render.py
proclamation/settings.py
proclamation/types.py
proclamation/utils.py
proclamation/templates/base.md
proclamation/test/__init__.py
proclamation/test/test_main.py
proclamation/test/test_merge.py
proclamation/test/test_project.py
proclamation/test/test_render.py
proclamation/test/test_settings.py
proclamation/test/test_types.py
proclamation-2.0.0.dist-info/entry_points.txt
proclamation-2.0.0.dist-info/WHEEL
proclamation-2.0.0.dist-info/METADATA
proclamation-2.0.0.dist-info/RECORD
