Metadata-Version: 2.1
Name: proclamation
Version: 2.0.0
Summary: Generate updates to a changelog file by combining fragments.
Author-email: Rylie Pavlik <rylie.pavlik@collabora.com>
Requires-Python: >=3.7
Classifier: Development Status :: 5 - Production/Stable
Classifier: Intended Audience :: Developers
Classifier: License :: OSI Approved :: Apache Software License
Classifier: Operating System :: OS Independent
Classifier: Programming Language :: Python :: 3
Classifier: Programming Language :: Python :: 3.10
Classifier: Programming Language :: Python :: 3.11
Classifier: Programming Language :: Python :: 3.12
Classifier: Programming Language :: Python :: 3.7
Classifier: Programming Language :: Python :: 3.8
Classifier: Programming Language :: Python :: 3.9
Requires-Dist: click >=7,<9
Requires-Dist: jinja2 >=2,<3.1
Project-URL: Documentation, https://proclamation.readthedocs.io
Project-URL: Home, https://gitlab.com/proclamation/proclamation
